[
    {
        "id": "b_box_building_8115",
        "min_x": 1137,
        "max_x": 1195,
        "min_y": 498,
        "max_y": 528,
        "label": "building"
    },
    {
        "id": "b_box_sidewalks_98183",
        "min_x": 0,
        "max_x": 815,
        "min_y": 652,
        "max_y": 964,
        "label": "sidewalks"
    },
    {
        "id": "b_box_sidewalks_232170",
        "min_x": 1538,
        "max_x": 1741,
        "min_y": 679,
        "max_y": 690,
        "label": "sidewalks"
    },
    {
        "id": "b_box_building_27113",
        "min_x": 680,
        "max_x": 768,
        "min_y": 483,
        "max_y": 654,
        "label": "building"
    },
    {
        "id": "b_box_static_183208",
        "min_x": 1672,
        "max_x": 1680,
        "min_y": 650,
        "max_y": 670,
        "label": "static"
    },
    {
        "id": "b_box_building_41185",
        "min_x": 1129,
        "max_x": 1237,
        "min_y": 502,
        "max_y": 592,
        "label": "building"
    },
    {
        "id": "b_box_building_220114",
        "min_x": 774,
        "max_x": 791,
        "min_y": 540,
        "max_y": 546,
        "label": "building"
    },
    {
        "id": "b_box_unknown_15145",
        "min_x": 1513,
        "max_x": 1527,
        "min_y": 736,
        "max_y": 777,
        "label": "unknown"
    },
    {
        "id": "b_box_vegetation_31185",
        "min_x": 1534,
        "max_x": 1541,
        "min_y": 650,
        "max_y": 656,
        "label": "vegetation"
    },
    {
        "id": "b_box_vegetation_249184",
        "min_x": 1514,
        "max_x": 1533,
        "min_y": 610,
        "max_y": 672,
        "label": "vegetation"
    },
    {
        "id": "b_box_vegetation_249184",
        "min_x": 1168,
        "max_x": 1819,
        "min_y": 0,
        "max_y": 533,
        "label": "vegetation"
    },
    {
        "id": "b_box_vegetation_249184",
        "min_x": 1523,
        "max_x": 1533,
        "min_y": 521,
        "max_y": 534,
        "label": "vegetation"
    },
    {
        "id": "b_box_vegetation_249184",
        "min_x": 1216,
        "max_x": 1222,
        "min_y": 479,
        "max_y": 485,
        "label": "vegetation"
    },
    {
        "id": "b_box_vegetation_249184",
        "min_x": 1793,
        "max_x": 1801,
        "min_y": 471,
        "max_y": 477,
        "label": "vegetation"
    },
    {
        "id": "b_box_vegetation_249184",
        "min_x": 1316,
        "max_x": 1326,
        "min_y": 455,
        "max_y": 463,
        "label": "vegetation"
    },
    {
        "id": "b_box_vegetation_249184",
        "min_x": 1224,
        "max_x": 1228,
        "min_y": 425,
        "max_y": 432,
        "label": "vegetation"
    },
    {
        "id": "b_box_vegetation_249184",
        "min_x": 1380,
        "max_x": 1499,
        "min_y": 410,
        "max_y": 457,
        "label": "vegetation"
    },
    {
        "id": "b_box_vegetation_249184",
        "min_x": 1248,
        "max_x": 1253,
        "min_y": 290,
        "max_y": 295,
        "label": "vegetation"
    },
    {
        "id": "b_box_vegetation_249184",
        "min_x": 1281,
        "max_x": 1286,
        "min_y": 226,
        "max_y": 232,
        "label": "vegetation"
    },
    {
        "id": "b_box_vegetation_249184",
        "min_x": 1327,
        "max_x": 1334,
        "min_y": 206,
        "max_y": 212,
        "label": "vegetation"
    },
    {
        "id": "b_box_vegetation_249184",
        "min_x": 1323,
        "max_x": 1328,
        "min_y": 165,
        "max_y": 170,
        "label": "vegetation"
    },
    {
        "id": "b_box_vegetation_249184",
        "min_x": 1698,
        "max_x": 1703,
        "min_y": 64,
        "max_y": 72,
        "label": "vegetation"
    },
    {
        "id": "b_box_vegetation_249184",
        "min_x": 1409,
        "max_x": 1415,
        "min_y": 41,
        "max_y": 48,
        "label": "vegetation"
    },
    {
        "id": "b_box_vegetation_249184",
        "min_x": 1574,
        "max_x": 1578,
        "min_y": 40,
        "max_y": 46,
        "label": "vegetation"
    },
    {
        "id": "b_box_vegetation_249184",
        "min_x": 1497,
        "max_x": 1504,
        "min_y": 39,
        "max_y": 45,
        "label": "vegetation"
    },
    {
        "id": "b_box_vegetation_249184",
        "min_x": 1624,
        "max_x": 1641,
        "min_y": 5,
        "max_y": 13,
        "label": "vegetation"
    },
    {
        "id": "b_box_static_10162",
        "min_x": 1326,
        "max_x": 1386,
        "min_y": 657,
        "max_y": 771,
        "label": "static"
    },
    {
        "id": "b_box_building_249184",
        "min_x": 1534,
        "max_x": 1819,
        "min_y": 419,
        "max_y": 552,
        "label": "building"
    },
    {
        "id": "b_box_building_249184",
        "min_x": 1196,
        "max_x": 1211,
        "min_y": 486,
        "max_y": 496,
        "label": "building"
    },
    {
        "id": "b_box_building_249184",
        "min_x": 1804,
        "max_x": 1819,
        "min_y": 448,
        "max_y": 471,
        "label": "building"
    },
    {
        "id": "b_box_building_249184",
        "min_x": 1549,
        "max_x": 1563,
        "min_y": 446,
        "max_y": 455,
        "label": "building"
    },
    {
        "id": "b_box_building_249184",
        "min_x": 1482,
        "max_x": 1561,
        "min_y": 217,
        "max_y": 272,
        "label": "building"
    },
    {
        "id": "b_box_static_188167",
        "min_x": 1073,
        "max_x": 1098,
        "min_y": 642,
        "max_y": 678,
        "label": "static"
    },
    {
        "id": "b_box_building_226114",
        "min_x": 778,
        "max_x": 807,
        "min_y": 544,
        "max_y": 558,
        "label": "building"
    },
    {
        "id": "b_box_building_128114",
        "min_x": 1507,
        "max_x": 1634,
        "min_y": 542,
        "max_y": 655,
        "label": "building"
    },
    {
        "id": "b_box_car_113245",
        "min_x": 1025,
        "max_x": 1078,
        "min_y": 631,
        "max_y": 662,
        "label": "car"
    },
    {
        "id": "b_box_rail_track_43185",
        "min_x": 1272,
        "max_x": 1365,
        "min_y": 431,
        "max_y": 477,
        "label": "rail_track"
    },
    {
        "id": "b_box_rail_track_43185",
        "min_x": 1419,
        "max_x": 1448,
        "min_y": 426,
        "max_y": 453,
        "label": "rail_track"
    },
    {
        "id": "b_box_building_239113",
        "min_x": 1051,
        "max_x": 1071,
        "min_y": 501,
        "max_y": 511,
        "label": "building"
    },
    {
        "id": "b_box_sidewalks_175179",
        "min_x": 0,
        "max_x": 742,
        "min_y": 655,
        "max_y": 839,
        "label": "sidewalks"
    },
    {
        "id": "b_box_building_24113",
        "min_x": 881,
        "max_x": 897,
        "min_y": 558,
        "max_y": 602,
        "label": "building"
    },
    {
        "id": "b_box_car_104246",
        "min_x": 992,
        "max_x": 1044,
        "min_y": 622,
        "max_y": 651,
        "label": "car"
    },
    {
        "id": "b_box_dynamic_1209",
        "min_x": 916,
        "max_x": 928,
        "min_y": 659,
        "max_y": 681,
        "label": "dynamic"
    },
    {
        "id": "b_box_pole_254144",
        "min_x": 1102,
        "max_x": 1237,
        "min_y": 405,
        "max_y": 623,
        "label": "pole"
    },
    {
        "id": "b_box_pole_254144",
        "min_x": 756,
        "max_x": 967,
        "min_y": 474,
        "max_y": 649,
        "label": "pole"
    },
    {
        "id": "b_box_pole_254144",
        "min_x": 1235,
        "max_x": 1254,
        "min_y": 491,
        "max_y": 498,
        "label": "pole"
    },
    {
        "id": "b_box_static_210167",
        "min_x": 1251,
        "max_x": 1357,
        "min_y": 668,
        "max_y": 759,
        "label": "static"
    },
    {
        "id": "b_box_sky_133116",
        "min_x": 778,
        "max_x": 806,
        "min_y": 531,
        "max_y": 537,
        "label": "sky"
    },
    {
        "id": "b_box_sky_133116",
        "min_x": 0,
        "max_x": 1583,
        "min_y": 0,
        "max_y": 498,
        "label": "sky"
    },
    {
        "id": "b_box_sky_133116",
        "min_x": 1737,
        "max_x": 1819,
        "min_y": 0,
        "max_y": 58,
        "label": "sky"
    },
    {
        "id": "b_box_roadLines_227176",
        "min_x": 779,
        "max_x": 826,
        "min_y": 654,
        "max_y": 670,
        "label": "roadLines"
    },
    {
        "id": "b_box_roadLines_227176",
        "min_x": 871,
        "max_x": 881,
        "min_y": 655,
        "max_y": 666,
        "label": "roadLines"
    },
    {
        "id": "b_box_dynamic_21209",
        "min_x": 991,
        "max_x": 1000,
        "min_y": 646,
        "max_y": 661,
        "label": "dynamic"
    },
    {
        "id": "b_box_building_225114",
        "min_x": 774,
        "max_x": 783,
        "min_y": 547,
        "max_y": 567,
        "label": "building"
    },
    {
        "id": "b_box_vegetation_73132",
        "min_x": 1330,
        "max_x": 1391,
        "min_y": 497,
        "max_y": 535,
        "label": "vegetation"
    },
    {
        "id": "b_box_vegetation_73132",
        "min_x": 1486,
        "max_x": 1520,
        "min_y": 501,
        "max_y": 525,
        "label": "vegetation"
    },
    {
        "id": "b_box_building_162114",
        "min_x": 821,
        "max_x": 859,
        "min_y": 524,
        "max_y": 556,
        "label": "building"
    },
    {
        "id": "b_box_roadLines_229176",
        "min_x": 393,
        "max_x": 543,
        "min_y": 1090,
        "max_y": 1239,
        "label": "roadLines"
    },
    {
        "id": "b_box_roadLines_229176",
        "min_x": 1276,
        "max_x": 1427,
        "min_y": 1089,
        "max_y": 1239,
        "label": "roadLines"
    },
    {
        "id": "b_box_pole_150109",
        "min_x": 742,
        "max_x": 903,
        "min_y": 437,
        "max_y": 661,
        "label": "pole"
    },
    {
        "id": "b_box_static_172167",
        "min_x": 1803,
        "max_x": 1819,
        "min_y": 681,
        "max_y": 716,
        "label": "static"
    },
    {
        "id": "b_box_building_124114",
        "min_x": 1624,
        "max_x": 1766,
        "min_y": 490,
        "max_y": 657,
        "label": "building"
    },
    {
        "id": "b_box_building_13115",
        "min_x": 881,
        "max_x": 897,
        "min_y": 547,
        "max_y": 563,
        "label": "building"
    },
    {
        "id": "b_box_building_13115",
        "min_x": 1101,
        "max_x": 1114,
        "min_y": 531,
        "max_y": 548,
        "label": "building"
    },
    {
        "id": "b_box_building_17145",
        "min_x": 1734,
        "max_x": 1739,
        "min_y": 634,
        "max_y": 653,
        "label": "building"
    },
    {
        "id": "b_box_building_17145",
        "min_x": 1777,
        "max_x": 1785,
        "min_y": 619,
        "max_y": 623,
        "label": "building"
    },
    {
        "id": "b_box_building_43185",
        "min_x": 1473,
        "max_x": 1541,
        "min_y": 509,
        "max_y": 626,
        "label": "building"
    },
    {
        "id": "b_box_building_43185",
        "min_x": 1257,
        "max_x": 1264,
        "min_y": 615,
        "max_y": 623,
        "label": "building"
    },
    {
        "id": "b_box_building_43185",
        "min_x": 1255,
        "max_x": 1359,
        "min_y": 471,
        "max_y": 571,
        "label": "building"
    },
    {
        "id": "b_box_building_43185",
        "min_x": 1431,
        "max_x": 1448,
        "min_y": 523,
        "max_y": 540,
        "label": "building"
    },
    {
        "id": "b_box_building_43185",
        "min_x": 1226,
        "max_x": 1249,
        "min_y": 507,
        "max_y": 541,
        "label": "building"
    },
    {
        "id": "b_box_sidewalks_84183",
        "min_x": 963,
        "max_x": 980,
        "min_y": 665,
        "max_y": 670,
        "label": "sidewalks"
    },
    {
        "id": "b_box_pole_41185",
        "min_x": 1109,
        "max_x": 1144,
        "min_y": 537,
        "max_y": 623,
        "label": "pole"
    },
    {
        "id": "b_box_pole_41185",
        "min_x": 1182,
        "max_x": 1229,
        "min_y": 497,
        "max_y": 518,
        "label": "pole"
    },
    {
        "id": "b_box_pole_210109",
        "min_x": 1044,
        "max_x": 1065,
        "min_y": 504,
        "max_y": 631,
        "label": "pole"
    },
    {
        "id": "b_box_building_227114",
        "min_x": 792,
        "max_x": 806,
        "min_y": 540,
        "max_y": 544,
        "label": "building"
    },
    {
        "id": "b_box_sidewalks_106183",
        "min_x": 1534,
        "max_x": 1738,
        "min_y": 661,
        "max_y": 670,
        "label": "sidewalks"
    },
    {
        "id": "b_box_pole_209109",
        "min_x": 874,
        "max_x": 880,
        "min_y": 526,
        "max_y": 642,
        "label": "pole"
    },
    {
        "id": "b_box_roadLines_231176",
        "min_x": 0,
        "max_x": 870,
        "min_y": 670,
        "max_y": 1089,
        "label": "roadLines"
    },
    {
        "id": "b_box_roadLines_231176",
        "min_x": 882,
        "max_x": 1301,
        "min_y": 671,
        "max_y": 1088,
        "label": "roadLines"
    },
    {
        "id": "b_box_sidewalks_228170",
        "min_x": 1534,
        "max_x": 1671,
        "min_y": 660,
        "max_y": 664,
        "label": "sidewalks"
    },
    {
        "id": "b_box_sky_249184",
        "min_x": 1223,
        "max_x": 1256,
        "min_y": 482,
        "max_y": 493,
        "label": "sky"
    },
    {
        "id": "b_box_sky_249184",
        "min_x": 1203,
        "max_x": 1693,
        "min_y": 0,
        "max_y": 351,
        "label": "sky"
    },
    {
        "id": "b_box_sky_249184",
        "min_x": 1290,
        "max_x": 1525,
        "min_y": 51,
        "max_y": 303,
        "label": "sky"
    },
    {
        "id": "b_box_sky_249184",
        "min_x": 1618,
        "max_x": 1819,
        "min_y": 0,
        "max_y": 175,
        "label": "sky"
    },
    {
        "id": "b_box_sky_249184",
        "min_x": 1634,
        "max_x": 1638,
        "min_y": 128,
        "max_y": 132,
        "label": "sky"
    },
    {
        "id": "b_box_sky_249184",
        "min_x": 1765,
        "max_x": 1783,
        "min_y": 111,
        "max_y": 118,
        "label": "sky"
    },
    {
        "id": "b_box_sky_249184",
        "min_x": 1515,
        "max_x": 1539,
        "min_y": 93,
        "max_y": 105,
        "label": "sky"
    },
    {
        "id": "b_box_pole_151109",
        "min_x": 608,
        "max_x": 892,
        "min_y": 301,
        "max_y": 693,
        "label": "pole"
    },
    {
        "id": "b_box_sidewalks_207170",
        "min_x": 978,
        "max_x": 1073,
        "min_y": 662,
        "max_y": 666,
        "label": "sidewalks"
    },
    {
        "id": "b_box_rail_track_218162",
        "min_x": 676,
        "max_x": 841,
        "min_y": 467,
        "max_y": 534,
        "label": "rail_track"
    },
    {
        "id": "b_box_building_113245",
        "min_x": 1051,
        "max_x": 1057,
        "min_y": 635,
        "max_y": 640,
        "label": "building"
    },
    {
        "id": "b_box_building_31185",
        "min_x": 1534,
        "max_x": 1545,
        "min_y": 648,
        "max_y": 654,
        "label": "building"
    },
    {
        "id": "b_box_rail_track_41145",
        "min_x": 753,
        "max_x": 1284,
        "min_y": 350,
        "max_y": 517,
        "label": "rail_track"
    },
    {
        "id": "b_box_rail_track_41145",
        "min_x": 1129,
        "max_x": 1162,
        "min_y": 457,
        "max_y": 485,
        "label": "rail_track"
    },
    {
        "id": "b_box_rail_track_41145",
        "min_x": 691,
        "max_x": 747,
        "min_y": 455,
        "max_y": 504,
        "label": "rail_track"
    },
    {
        "id": "b_box_building_30113",
        "min_x": 192,
        "max_x": 529,
        "min_y": 235,
        "max_y": 724,
        "label": "building"
    },
    {
        "id": "b_box_unknown_179179",
        "min_x": 1025,
        "max_x": 1819,
        "min_y": 665,
        "max_y": 997,
        "label": "unknown"
    },
    {
        "id": "b_box_roads_210173",
        "min_x": 0,
        "max_x": 1396,
        "min_y": 671,
        "max_y": 1091,
        "label": "roads"
    },
    {
        "id": "b_box_building_73132",
        "min_x": 1502,
        "max_x": 1515,
        "min_y": 506,
        "max_y": 525,
        "label": "building"
    },
    {
        "id": "b_box_building_206246",
        "min_x": 982,
        "max_x": 998,
        "min_y": 600,
        "max_y": 619,
        "label": "building"
    },
    {
        "id": "b_box_static_43185",
        "min_x": 1265,
        "max_x": 1282,
        "min_y": 607,
        "max_y": 622,
        "label": "static"
    },
    {
        "id": "b_box_dynamic_249208",
        "min_x": 1638,
        "max_x": 1652,
        "min_y": 641,
        "max_y": 660,
        "label": "dynamic"
    },
    {
        "id": "b_box_building_71132",
        "min_x": 1077,
        "max_x": 1091,
        "min_y": 577,
        "max_y": 587,
        "label": "building"
    },
    {
        "id": "b_box_sidewalks_222170",
        "min_x": 978,
        "max_x": 1819,
        "min_y": 667,
        "max_y": 1239,
        "label": "sidewalks"
    },
    {
        "id": "b_box_vegetation_17145",
        "min_x": 1736,
        "max_x": 1819,
        "min_y": 620,
        "max_y": 700,
        "label": "vegetation"
    },
    {
        "id": "b_box_static_15145",
        "min_x": 1521,
        "max_x": 1531,
        "min_y": 688,
        "max_y": 722,
        "label": "static"
    },
    {
        "id": "b_box_building_29113",
        "min_x": 499,
        "max_x": 655,
        "min_y": 378,
        "max_y": 682,
        "label": "building"
    },
    {
        "id": "b_box_building_104246",
        "min_x": 1002,
        "max_x": 1035,
        "min_y": 625,
        "max_y": 630,
        "label": "building"
    },
    {
        "id": "b_box_roads_245173",
        "min_x": 1534,
        "max_x": 1739,
        "min_y": 665,
        "max_y": 686,
        "label": "roads"
    },
    {
        "id": "b_box_pole_73132",
        "min_x": 1324,
        "max_x": 1527,
        "min_y": 405,
        "max_y": 788,
        "label": "pole"
    },
    {
        "id": "b_box_sidewalks_96183",
        "min_x": 964,
        "max_x": 1792,
        "min_y": 667,
        "max_y": 1239,
        "label": "sidewalks"
    },
    {
        "id": "b_box_dynamic_240208",
        "min_x": 590,
        "max_x": 596,
        "min_y": 661,
        "max_y": 703,
        "label": "dynamic"
    },
    {
        "id": "b_box_building_3114",
        "min_x": 1030,
        "max_x": 1097,
        "min_y": 550,
        "max_y": 637,
        "label": "building"
    },
    {
        "id": "b_box_building_72132",
        "min_x": 1712,
        "max_x": 1782,
        "min_y": 548,
        "max_y": 566,
        "label": "building"
    },
    {
        "id": "b_box_pole_43185",
        "min_x": 1279,
        "max_x": 1283,
        "min_y": 620,
        "max_y": 624,
        "label": "pole"
    },
    {
        "id": "b_box_pole_43185",
        "min_x": 1227,
        "max_x": 1295,
        "min_y": 476,
        "max_y": 521,
        "label": "pole"
    },
    {
        "id": "b_box_building_221113",
        "min_x": 1129,
        "max_x": 1184,
        "min_y": 490,
        "max_y": 527,
        "label": "building"
    },
    {
        "id": "b_box_truck_206246",
        "min_x": 879,
        "max_x": 998,
        "min_y": 596,
        "max_y": 651,
        "label": "truck"
    },
    {
        "id": "b_box_building_26115",
        "min_x": 894,
        "max_x": 984,
        "min_y": 512,
        "max_y": 596,
        "label": "building"
    },
    {
        "id": "b_box_building_225113",
        "min_x": 1072,
        "max_x": 1114,
        "min_y": 497,
        "max_y": 531,
        "label": "building"
    },
    {
        "id": "b_box_vegetation_43185",
        "min_x": 1231,
        "max_x": 1399,
        "min_y": 427,
        "max_y": 629,
        "label": "vegetation"
    },
    {
        "id": "b_box_vegetation_43185",
        "min_x": 1378,
        "max_x": 1540,
        "min_y": 428,
        "max_y": 639,
        "label": "vegetation"
    },
    {
        "id": "b_box_vegetation_43185",
        "min_x": 1346,
        "max_x": 1373,
        "min_y": 429,
        "max_y": 504,
        "label": "vegetation"
    },
    {
        "id": "b_box_static_199208",
        "min_x": 691,
        "max_x": 700,
        "min_y": 649,
        "max_y": 664,
        "label": "static"
    },
    {
        "id": "b_box_building_26113",
        "min_x": 0,
        "max_x": 209,
        "min_y": 179,
        "max_y": 774,
        "label": "building"
    },
    {
        "id": "b_box_vegetation_71132",
        "min_x": 1130,
        "max_x": 1137,
        "min_y": 578,
        "max_y": 586,
        "label": "vegetation"
    },
    {
        "id": "b_box_pole_113245",
        "min_x": 1059,
        "max_x": 1067,
        "min_y": 633,
        "max_y": 639,
        "label": "pole"
    },
    {
        "id": "b_box_sidewalks_224170",
        "min_x": 0,
        "max_x": 806,
        "min_y": 652,
        "max_y": 908,
        "label": "sidewalks"
    },
    {
        "id": "b_box_static_170167",
        "min_x": 1522,
        "max_x": 1546,
        "min_y": 688,
        "max_y": 736,
        "label": "static"
    },
    {
        "id": "b_box_truck_41185",
        "min_x": 1182,
        "max_x": 1189,
        "min_y": 615,
        "max_y": 623,
        "label": "truck"
    },
    {
        "id": "b_box_dynamic_187208",
        "min_x": 1650,
        "max_x": 1698,
        "min_y": 704,
        "max_y": 791,
        "label": "dynamic"
    },
    {
        "id": "b_box_pole_72132",
        "min_x": 1708,
        "max_x": 1819,
        "min_y": 500,
        "max_y": 710,
        "label": "pole"
    },
    {
        "id": "b_box_building_236113",
        "min_x": 860,
        "max_x": 913,
        "min_y": 520,
        "max_y": 559,
        "label": "building"
    },
    {
        "id": "b_box_sidewalks_250144",
        "min_x": 1540,
        "max_x": 1819,
        "min_y": 683,
        "max_y": 933,
        "label": "sidewalks"
    },
    {
        "id": "b_box_building_161114",
        "min_x": 807,
        "max_x": 832,
        "min_y": 528,
        "max_y": 554,
        "label": "building"
    },
    {
        "id": "b_box_roads_200173",
        "min_x": 782,
        "max_x": 1028,
        "min_y": 645,
        "max_y": 670,
        "label": "roads"
    },
    {
        "id": "b_box_building_28113",
        "min_x": 602,
        "max_x": 730,
        "min_y": 440,
        "max_y": 663,
        "label": "building"
    },
    {
        "id": "b_box_building_25115",
        "min_x": 961,
        "max_x": 1061,
        "min_y": 504,
        "max_y": 631,
        "label": "building"
    },
    {
        "id": "b_box_building_25115",
        "min_x": 1049,
        "max_x": 1105,
        "min_y": 504,
        "max_y": 551,
        "label": "building"
    },
    {
        "id": "b_box_building_7115",
        "min_x": 1227,
        "max_x": 1238,
        "min_y": 493,
        "max_y": 514,
        "label": "building"
    },
    {
        "id": "b_box_rail_track_249184",
        "min_x": 1163,
        "max_x": 1357,
        "min_y": 324,
        "max_y": 486,
        "label": "rail_track"
    },
    {
        "id": "b_box_rail_track_249184",
        "min_x": 1254,
        "max_x": 1370,
        "min_y": 410,
        "max_y": 474,
        "label": "rail_track"
    },
    {
        "id": "b_box_rail_track_249184",
        "min_x": 1438,
        "max_x": 1476,
        "min_y": 395,
        "max_y": 431,
        "label": "rail_track"
    },
    {
        "id": "b_box_rail_track_249184",
        "min_x": 1768,
        "max_x": 1819,
        "min_y": 396,
        "max_y": 421,
        "label": "rail_track"
    },
    {
        "id": "b_box_rail_track_249184",
        "min_x": 1390,
        "max_x": 1407,
        "min_y": 330,
        "max_y": 343,
        "label": "rail_track"
    },
    {
        "id": "b_box_rail_track_249184",
        "min_x": 1487,
        "max_x": 1519,
        "min_y": 305,
        "max_y": 333,
        "label": "rail_track"
    },
    {
        "id": "b_box_rail_track_249184",
        "min_x": 1753,
        "max_x": 1819,
        "min_y": 217,
        "max_y": 333,
        "label": "rail_track"
    },
    {
        "id": "b_box_rail_track_249184",
        "min_x": 1605,
        "max_x": 1656,
        "min_y": 267,
        "max_y": 295,
        "label": "rail_track"
    },
    {
        "id": "b_box_rail_track_249184",
        "min_x": 1698,
        "max_x": 1752,
        "min_y": 251,
        "max_y": 288,
        "label": "rail_track"
    },
    {
        "id": "b_box_building_25113",
        "min_x": 776,
        "max_x": 877,
        "min_y": 552,
        "max_y": 639,
        "label": "building"
    },
    {
        "id": "b_box_sidewalks_181179",
        "min_x": 1564,
        "max_x": 1737,
        "min_y": 655,
        "max_y": 662,
        "label": "sidewalks"
    },
    {
        "id": "b_box_vegetation_41185",
        "min_x": 1120,
        "max_x": 1257,
        "min_y": 508,
        "max_y": 626,
        "label": "vegetation"
    },
    {
        "id": "b_box_pole_71132",
        "min_x": 1075,
        "max_x": 1139,
        "min_y": 545,
        "max_y": 679,
        "label": "pole"
    },
    {
        "id": "b_box_roads_203173",
        "min_x": 0,
        "max_x": 1549,
        "min_y": 1092,
        "max_y": 1239,
        "label": "roads"
    },
    {
        "id": "b_box_vegetation_15145",
        "min_x": 1077,
        "max_x": 1399,
        "min_y": 622,
        "max_y": 761,
        "label": "vegetation"
    },
    {
        "id": "b_box_vegetation_15145",
        "min_x": 1078,
        "max_x": 1098,
        "min_y": 655,
        "max_y": 671,
        "label": "vegetation"
    },
    {
        "id": "b_box_vegetation_15145",
        "min_x": 1410,
        "max_x": 1533,
        "min_y": 626,
        "max_y": 779,
        "label": "vegetation"
    },
    {
        "id": "b_box_pole_249184",
        "min_x": 1550,
        "max_x": 1556,
        "min_y": 519,
        "max_y": 542,
        "label": "pole"
    },
    {
        "id": "b_box_pole_249184",
        "min_x": 1163,
        "max_x": 1272,
        "min_y": 444,
        "max_y": 496,
        "label": "pole"
    },
    {
        "id": "b_box_building_123114",
        "min_x": 1773,
        "max_x": 1819,
        "min_y": 485,
        "max_y": 623,
        "label": "building"
    },
    {
        "id": "b_box_pole_212109",
        "min_x": 1544,
        "max_x": 1563,
        "min_y": 543,
        "max_y": 659,
        "label": "pole"
    }
]