[
    {
        "id": "b_box_sidewalks_255180",
        "min_x": 1067,
        "max_x": 1110,
        "min_y": 643,
        "max_y": 648,
        "label": "sidewalks"
    },
    {
        "id": "b_box_roadLines_84178",
        "min_x": 835,
        "max_x": 842,
        "min_y": 644,
        "max_y": 648,
        "label": "roadLines"
    },
    {
        "id": "b_box_roadLines_84178",
        "min_x": 913,
        "max_x": 925,
        "min_y": 639,
        "max_y": 648,
        "label": "roadLines"
    },
    {
        "id": "b_box_building_62115",
        "min_x": 1147,
        "max_x": 1234,
        "min_y": 389,
        "max_y": 635,
        "label": "building"
    },
    {
        "id": "b_box_building_62115",
        "min_x": 1245,
        "max_x": 1250,
        "min_y": 390,
        "max_y": 399,
        "label": "building"
    },
    {
        "id": "b_box_bicycle_1014",
        "min_x": 127,
        "max_x": 141,
        "min_y": 660,
        "max_y": 690,
        "label": "bicycle"
    },
    {
        "id": "b_box_pole_73145",
        "min_x": 8,
        "max_x": 544,
        "min_y": 443,
        "max_y": 646,
        "label": "pole"
    },
    {
        "id": "b_box_sidewalks_11181",
        "min_x": 653,
        "max_x": 766,
        "min_y": 636,
        "max_y": 648,
        "label": "sidewalks"
    },
    {
        "id": "b_box_ground_226163",
        "min_x": 23,
        "max_x": 187,
        "min_y": 682,
        "max_y": 721,
        "label": "ground"
    },
    {
        "id": "b_box_ground_226163",
        "min_x": 272,
        "max_x": 546,
        "min_y": 661,
        "max_y": 693,
        "label": "ground"
    },
    {
        "id": "b_box_dynamic_733",
        "min_x": 1341,
        "max_x": 1368,
        "min_y": 657,
        "max_y": 672,
        "label": "dynamic"
    },
    {
        "id": "b_box_sidewalks_13181",
        "min_x": 637,
        "max_x": 717,
        "min_y": 638,
        "max_y": 646,
        "label": "sidewalks"
    },
    {
        "id": "b_box_dynamic_11163",
        "min_x": 427,
        "max_x": 440,
        "min_y": 643,
        "max_y": 659,
        "label": "dynamic"
    },
    {
        "id": "b_box_pedestrian_625",
        "min_x": 449,
        "max_x": 453,
        "min_y": 625,
        "max_y": 629,
        "label": "pedestrian"
    },
    {
        "id": "b_box_roadLines_227184",
        "min_x": 459,
        "max_x": 544,
        "min_y": 734,
        "max_y": 759,
        "label": "roadLines"
    },
    {
        "id": "b_box_building_78115",
        "min_x": 1479,
        "max_x": 1597,
        "min_y": 293,
        "max_y": 355,
        "label": "building"
    },
    {
        "id": "b_box_motorcycle_2103",
        "min_x": 773,
        "max_x": 846,
        "min_y": 657,
        "max_y": 699,
        "label": "motorcycle"
    },
    {
        "id": "b_box_pole_141111",
        "min_x": 617,
        "max_x": 630,
        "min_y": 543,
        "max_y": 555,
        "label": "pole"
    },
    {
        "id": "b_box_static_1373",
        "min_x": 176,
        "max_x": 278,
        "min_y": 610,
        "max_y": 778,
        "label": "static"
    },
    {
        "id": "b_box_roadLines_229184",
        "min_x": 264,
        "max_x": 356,
        "min_y": 733,
        "max_y": 754,
        "label": "roadLines"
    },
    {
        "id": "b_box_walls_156145",
        "min_x": 960,
        "max_x": 986,
        "min_y": 518,
        "max_y": 546,
        "label": "walls"
    },
    {
        "id": "b_box_cyclist_505",
        "min_x": 430,
        "max_x": 436,
        "min_y": 626,
        "max_y": 635,
        "label": "cyclist"
    },
    {
        "id": "b_box_roadLines_88178",
        "min_x": 619,
        "max_x": 641,
        "min_y": 652,
        "max_y": 660,
        "label": "roadLines"
    },
    {
        "id": "b_box_static_813",
        "min_x": 306,
        "max_x": 345,
        "min_y": 808,
        "max_y": 951,
        "label": "static"
    },
    {
        "id": "b_box_pole_46132",
        "min_x": 1002,
        "max_x": 1008,
        "min_y": 528,
        "max_y": 535,
        "label": "pole"
    },
    {
        "id": "b_box_walls_0145",
        "min_x": 1083,
        "max_x": 1170,
        "min_y": 535,
        "max_y": 644,
        "label": "walls"
    },
    {
        "id": "b_box_building_9185",
        "min_x": 8,
        "max_x": 204,
        "min_y": 487,
        "max_y": 610,
        "label": "building"
    },
    {
        "id": "b_box_building_9185",
        "min_x": 189,
        "max_x": 269,
        "min_y": 516,
        "max_y": 523,
        "label": "building"
    },
    {
        "id": "b_box_building_9185",
        "min_x": 111,
        "max_x": 289,
        "min_y": 292,
        "max_y": 386,
        "label": "building"
    },
    {
        "id": "b_box_sky_133116",
        "min_x": 0,
        "max_x": 1819,
        "min_y": 0,
        "max_y": 546,
        "label": "sky"
    },
    {
        "id": "b_box_sidewalks_76162",
        "min_x": 1278,
        "max_x": 1671,
        "min_y": 534,
        "max_y": 712,
        "label": "sidewalks"
    },
    {
        "id": "b_box_car_187187",
        "min_x": 427,
        "max_x": 443,
        "min_y": 640,
        "max_y": 653,
        "label": "car"
    },
    {
        "id": "b_box_pole_1126",
        "min_x": 913,
        "max_x": 988,
        "min_y": 556,
        "max_y": 646,
        "label": "pole"
    },
    {
        "id": "b_box_sidewalks_27181",
        "min_x": 0,
        "max_x": 182,
        "min_y": 716,
        "max_y": 753,
        "label": "sidewalks"
    },
    {
        "id": "b_box_sidewalks_27181",
        "min_x": 278,
        "max_x": 595,
        "min_y": 663,
        "max_y": 712,
        "label": "sidewalks"
    },
    {
        "id": "b_box_pedestrian_1065",
        "min_x": 896,
        "max_x": 909,
        "min_y": 630,
        "max_y": 687,
        "label": "pedestrian"
    },
    {
        "id": "b_box_dynamic_19163",
        "min_x": 512,
        "max_x": 521,
        "min_y": 639,
        "max_y": 654,
        "label": "dynamic"
    },
    {
        "id": "b_box_dynamic_1213",
        "min_x": 1029,
        "max_x": 1100,
        "min_y": 898,
        "max_y": 1014,
        "label": "dynamic"
    },
    {
        "id": "b_box_dynamic_7163",
        "min_x": 457,
        "max_x": 471,
        "min_y": 641,
        "max_y": 658,
        "label": "dynamic"
    },
    {
        "id": "b_box_motorcycle_2393",
        "min_x": 1036,
        "max_x": 1071,
        "min_y": 640,
        "max_y": 659,
        "label": "motorcycle"
    },
    {
        "id": "b_box_car_636",
        "min_x": 767,
        "max_x": 813,
        "min_y": 629,
        "max_y": 643,
        "label": "car"
    },
    {
        "id": "b_box_dynamic_13163",
        "min_x": 545,
        "max_x": 549,
        "min_y": 644,
        "max_y": 651,
        "label": "dynamic"
    },
    {
        "id": "b_box_sidewalks_29181",
        "min_x": 1218,
        "max_x": 1819,
        "min_y": 695,
        "max_y": 874,
        "label": "sidewalks"
    },
    {
        "id": "b_box_sidewalks_29181",
        "min_x": 1075,
        "max_x": 1113,
        "min_y": 663,
        "max_y": 676,
        "label": "sidewalks"
    },
    {
        "id": "b_box_building_63115",
        "min_x": 1570,
        "max_x": 1671,
        "min_y": 234,
        "max_y": 540,
        "label": "building"
    },
    {
        "id": "b_box_other_853",
        "min_x": 653,
        "max_x": 728,
        "min_y": 697,
        "max_y": 708,
        "label": "other"
    },
    {
        "id": "b_box_dynamic_1293",
        "min_x": 1321,
        "max_x": 1378,
        "min_y": 667,
        "max_y": 724,
        "label": "dynamic"
    },
    {
        "id": "b_box_cyclist_2103",
        "min_x": 795,
        "max_x": 823,
        "min_y": 640,
        "max_y": 697,
        "label": "cyclist"
    },
    {
        "id": "b_box_static_773",
        "min_x": 744,
        "max_x": 767,
        "min_y": 733,
        "max_y": 814,
        "label": "static"
    },
    {
        "id": "b_box_sidewalks_7181",
        "min_x": 942,
        "max_x": 969,
        "min_y": 637,
        "max_y": 646,
        "label": "sidewalks"
    },
    {
        "id": "b_box_pole_138109",
        "min_x": 982,
        "max_x": 1256,
        "min_y": 310,
        "max_y": 690,
        "label": "pole"
    },
    {
        "id": "b_box_pole_137109",
        "min_x": 0,
        "max_x": 423,
        "min_y": 125,
        "max_y": 734,
        "label": "pole"
    },
    {
        "id": "b_box_roads_4175",
        "min_x": 0,
        "max_x": 873,
        "min_y": 666,
        "max_y": 1239,
        "label": "roads"
    },
    {
        "id": "b_box_roads_4175",
        "min_x": 463,
        "max_x": 1819,
        "min_y": 666,
        "max_y": 1239,
        "label": "roads"
    },
    {
        "id": "b_box_sidewalks_9181",
        "min_x": 935,
        "max_x": 963,
        "min_y": 637,
        "max_y": 648,
        "label": "sidewalks"
    },
    {
        "id": "b_box_traffic_light_251125",
        "min_x": 540,
        "max_x": 574,
        "min_y": 548,
        "max_y": 567,
        "label": "traffic_light"
    },
    {
        "id": "b_box_building_71125",
        "min_x": 1035,
        "max_x": 1079,
        "min_y": 517,
        "max_y": 535,
        "label": "building"
    },
    {
        "id": "b_box_car_189187",
        "min_x": 427,
        "max_x": 468,
        "min_y": 630,
        "max_y": 652,
        "label": "car"
    },
    {
        "id": "b_box_sidewalks_158171",
        "min_x": 1219,
        "max_x": 1819,
        "min_y": 681,
        "max_y": 838,
        "label": "sidewalks"
    },
    {
        "id": "b_box_sidewalks_158171",
        "min_x": 1089,
        "max_x": 1114,
        "min_y": 663,
        "max_y": 668,
        "label": "sidewalks"
    },
    {
        "id": "b_box_pole_139109",
        "min_x": 488,
        "max_x": 689,
        "min_y": 398,
        "max_y": 671,
        "label": "pole"
    },
    {
        "id": "b_box_dynamic_21163",
        "min_x": 505,
        "max_x": 512,
        "min_y": 639,
        "max_y": 654,
        "label": "dynamic"
    },
    {
        "id": "b_box_walls_636",
        "min_x": 794,
        "max_x": 802,
        "min_y": 631,
        "max_y": 635,
        "label": "walls"
    },
    {
        "id": "b_box_dynamic_9163",
        "min_x": 441,
        "max_x": 457,
        "min_y": 642,
        "max_y": 658,
        "label": "dynamic"
    },
    {
        "id": "b_box_building_65164",
        "min_x": 899,
        "max_x": 933,
        "min_y": 522,
        "max_y": 545,
        "label": "building"
    },
    {
        "id": "b_box_car_197187",
        "min_x": 457,
        "max_x": 495,
        "min_y": 629,
        "max_y": 650,
        "label": "car"
    },
    {
        "id": "b_box_building_197166",
        "min_x": 603,
        "max_x": 742,
        "min_y": 507,
        "max_y": 546,
        "label": "building"
    },
    {
        "id": "b_box_sidewalks_23181",
        "min_x": 588,
        "max_x": 604,
        "min_y": 661,
        "max_y": 665,
        "label": "sidewalks"
    },
    {
        "id": "b_box_bicycle_2194",
        "min_x": 956,
        "max_x": 979,
        "min_y": 645,
        "max_y": 667,
        "label": "bicycle"
    },
    {
        "id": "b_box_bridge_81162",
        "min_x": 659,
        "max_x": 980,
        "min_y": 547,
        "max_y": 580,
        "label": "bridge"
    },
    {
        "id": "b_box_roads_2175",
        "min_x": 824,
        "max_x": 1108,
        "min_y": 648,
        "max_y": 665,
        "label": "roads"
    },
    {
        "id": "b_box_roads_2175",
        "min_x": 581,
        "max_x": 713,
        "min_y": 652,
        "max_y": 663,
        "label": "roads"
    },
    {
        "id": "b_box_sidewalks_152171",
        "min_x": 0,
        "max_x": 184,
        "min_y": 705,
        "max_y": 739,
        "label": "sidewalks"
    },
    {
        "id": "b_box_sidewalks_152171",
        "min_x": 278,
        "max_x": 580,
        "min_y": 663,
        "max_y": 702,
        "label": "sidewalks"
    },
    {
        "id": "b_box_pole_254125",
        "min_x": 522,
        "max_x": 779,
        "min_y": 484,
        "max_y": 662,
        "label": "pole"
    },
    {
        "id": "b_box_walls_182162",
        "min_x": 717,
        "max_x": 914,
        "min_y": 586,
        "max_y": 637,
        "label": "walls"
    },
    {
        "id": "b_box_walls_182162",
        "min_x": 939,
        "max_x": 952,
        "min_y": 595,
        "max_y": 631,
        "label": "walls"
    },
    {
        "id": "b_box_building_89125",
        "min_x": 1076,
        "max_x": 1110,
        "min_y": 488,
        "max_y": 535,
        "label": "building"
    },
    {
        "id": "b_box_walls_195162",
        "min_x": 172,
        "max_x": 696,
        "min_y": 523,
        "max_y": 647,
        "label": "walls"
    },
    {
        "id": "b_box_dynamic_17163",
        "min_x": 530,
        "max_x": 534,
        "min_y": 640,
        "max_y": 652,
        "label": "dynamic"
    },
    {
        "id": "b_box_pedestrian_945",
        "min_x": 546,
        "max_x": 558,
        "min_y": 626,
        "max_y": 658,
        "label": "pedestrian"
    },
    {
        "id": "b_box_sidewalks_143164",
        "min_x": 1220,
        "max_x": 1321,
        "min_y": 673,
        "max_y": 691,
        "label": "sidewalks"
    },
    {
        "id": "b_box_sidewalks_143164",
        "min_x": 1104,
        "max_x": 1114,
        "min_y": 657,
        "max_y": 661,
        "label": "sidewalks"
    },
    {
        "id": "b_box_dynamic_5163",
        "min_x": 472,
        "max_x": 486,
        "min_y": 640,
        "max_y": 657,
        "label": "dynamic"
    },
    {
        "id": "b_box_building_55115",
        "min_x": 1642,
        "max_x": 1819,
        "min_y": 2,
        "max_y": 784,
        "label": "building"
    },
    {
        "id": "b_box_pole_142109",
        "min_x": 998,
        "max_x": 1120,
        "min_y": 450,
        "max_y": 657,
        "label": "pole"
    },
    {
        "id": "b_box_sidewalks_145164",
        "min_x": 1390,
        "max_x": 1819,
        "min_y": 710,
        "max_y": 797,
        "label": "sidewalks"
    },
    {
        "id": "b_box_roadLines_221184",
        "min_x": 905,
        "max_x": 919,
        "min_y": 686,
        "max_y": 692,
        "label": "roadLines"
    },
    {
        "id": "b_box_unknown_199163",
        "min_x": 141,
        "max_x": 171,
        "min_y": 535,
        "max_y": 610,
        "label": "unknown"
    },
    {
        "id": "b_box_roads_254174",
        "min_x": 665,
        "max_x": 763,
        "min_y": 638,
        "max_y": 648,
        "label": "roads"
    },
    {
        "id": "b_box_roads_254174",
        "min_x": 823,
        "max_x": 899,
        "min_y": 634,
        "max_y": 648,
        "label": "roads"
    },
    {
        "id": "b_box_roads_254174",
        "min_x": 906,
        "max_x": 956,
        "min_y": 634,
        "max_y": 648,
        "label": "roads"
    },
    {
        "id": "b_box_roadLines_201184",
        "min_x": 1000,
        "max_x": 1059,
        "min_y": 686,
        "max_y": 692,
        "label": "roadLines"
    },
    {
        "id": "b_box_dynamic_1613",
        "min_x": 713,
        "max_x": 722,
        "min_y": 638,
        "max_y": 654,
        "label": "dynamic"
    },
    {
        "id": "b_box_building_56115",
        "min_x": 1178,
        "max_x": 1628,
        "min_y": 326,
        "max_y": 676,
        "label": "building"
    },
    {
        "id": "b_box_building_56115",
        "min_x": 1229,
        "max_x": 1234,
        "min_y": 435,
        "max_y": 441,
        "label": "building"
    },
    {
        "id": "b_box_cyclist_2393",
        "min_x": 1045,
        "max_x": 1061,
        "min_y": 633,
        "max_y": 659,
        "label": "cyclist"
    },
    {
        "id": "b_box_pole_45132",
        "min_x": 1044,
        "max_x": 1073,
        "min_y": 482,
        "max_y": 534,
        "label": "pole"
    },
    {
        "id": "b_box_rail_track_52145",
        "min_x": 7,
        "max_x": 496,
        "min_y": 270,
        "max_y": 523,
        "label": "rail_track"
    },
    {
        "id": "b_box_rail_track_52145",
        "min_x": 504,
        "max_x": 620,
        "min_y": 473,
        "max_y": 523,
        "label": "rail_track"
    },
    {
        "id": "b_box_rail_track_52145",
        "min_x": 83,
        "max_x": 132,
        "min_y": 487,
        "max_y": 491,
        "label": "rail_track"
    },
    {
        "id": "b_box_cyclist_1744",
        "min_x": 844,
        "max_x": 852,
        "min_y": 626,
        "max_y": 653,
        "label": "cyclist"
    },
    {
        "id": "b_box_building_30164",
        "min_x": 324,
        "max_x": 399,
        "min_y": 400,
        "max_y": 430,
        "label": "building"
    },
    {
        "id": "b_box_car_226",
        "min_x": 710,
        "max_x": 824,
        "min_y": 637,
        "max_y": 673,
        "label": "car"
    },
    {
        "id": "b_box_walls_35145",
        "min_x": 910,
        "max_x": 942,
        "min_y": 593,
        "max_y": 635,
        "label": "walls"
    },
    {
        "id": "b_box_walls_35145",
        "min_x": 849,
        "max_x": 873,
        "min_y": 589,
        "max_y": 637,
        "label": "walls"
    },
    {
        "id": "b_box_walls_201162",
        "min_x": 964,
        "max_x": 1083,
        "min_y": 535,
        "max_y": 647,
        "label": "walls"
    },
    {
        "id": "b_box_rail_track_214162",
        "min_x": 592,
        "max_x": 693,
        "min_y": 519,
        "max_y": 546,
        "label": "rail_track"
    },
    {
        "id": "b_box_bridge_139168",
        "min_x": 712,
        "max_x": 819,
        "min_y": 581,
        "max_y": 585,
        "label": "bridge"
    },
    {
        "id": "b_box_roads_226",
        "min_x": 745,
        "max_x": 765,
        "min_y": 640,
        "max_y": 648,
        "label": "roads"
    },
    {
        "id": "b_box_dynamic_1163",
        "min_x": 487,
        "max_x": 495,
        "min_y": 640,
        "max_y": 656,
        "label": "dynamic"
    },
    {
        "id": "b_box_cyclist_1014",
        "min_x": 124,
        "max_x": 149,
        "min_y": 628,
        "max_y": 689,
        "label": "cyclist"
    },
    {
        "id": "b_box_walls_197187",
        "min_x": 478,
        "max_x": 489,
        "min_y": 632,
        "max_y": 636,
        "label": "walls"
    },
    {
        "id": "b_box_dynamic_15163",
        "min_x": 535,
        "max_x": 545,
        "min_y": 637,
        "max_y": 651,
        "label": "dynamic"
    },
    {
        "id": "b_box_building_94126",
        "min_x": 1106,
        "max_x": 1170,
        "min_y": 461,
        "max_y": 535,
        "label": "building"
    },
    {
        "id": "b_box_pole_251125",
        "min_x": 547,
        "max_x": 589,
        "min_y": 523,
        "max_y": 647,
        "label": "pole"
    },
    {
        "id": "b_box_cyclist_2194",
        "min_x": 962,
        "max_x": 976,
        "min_y": 629,
        "max_y": 662,
        "label": "cyclist"
    },
    {
        "id": "b_box_roads_2194",
        "min_x": 957,
        "max_x": 964,
        "min_y": 654,
        "max_y": 660,
        "label": "roads"
    },
    {
        "id": "b_box_static_1533",
        "min_x": 1109,
        "max_x": 1221,
        "min_y": 628,
        "max_y": 794,
        "label": "static"
    },
    {
        "id": "b_box_walls_142161",
        "min_x": 953,
        "max_x": 986,
        "min_y": 580,
        "max_y": 645,
        "label": "walls"
    },
    {
        "id": "b_box_walls_142161",
        "min_x": 801,
        "max_x": 843,
        "min_y": 579,
        "max_y": 647,
        "label": "walls"
    },
    {
        "id": "b_box_walls_142161",
        "min_x": 637,
        "max_x": 716,
        "min_y": 579,
        "max_y": 645,
        "label": "walls"
    },
    {
        "id": "b_box_dynamic_1173",
        "min_x": 584,
        "max_x": 598,
        "min_y": 638,
        "max_y": 658,
        "label": "dynamic"
    },
    {
        "id": "b_box_pole_44132",
        "min_x": 1015,
        "max_x": 1038,
        "min_y": 508,
        "max_y": 535,
        "label": "pole"
    },
    {
        "id": "b_box_walls_13145",
        "min_x": 9,
        "max_x": 205,
        "min_y": 609,
        "max_y": 696,
        "label": "walls"
    },
    {
        "id": "b_box_walls_13145",
        "min_x": 229,
        "max_x": 426,
        "min_y": 612,
        "max_y": 674,
        "label": "walls"
    },
    {
        "id": "b_box_traffic_light_254125",
        "min_x": 631,
        "max_x": 637,
        "min_y": 529,
        "max_y": 545,
        "label": "traffic_light"
    },
    {
        "id": "b_box_traffic_light_254125",
        "min_x": 695,
        "max_x": 700,
        "min_y": 528,
        "max_y": 545,
        "label": "traffic_light"
    },
    {
        "id": "b_box_traffic_light_254125",
        "min_x": 769,
        "max_x": 774,
        "min_y": 527,
        "max_y": 545,
        "label": "traffic_light"
    },
    {
        "id": "b_box_roadLines_102178",
        "min_x": 0,
        "max_x": 305,
        "min_y": 837,
        "max_y": 990,
        "label": "roadLines"
    },
    {
        "id": "b_box_roadLines_102178",
        "min_x": 345,
        "max_x": 876,
        "min_y": 666,
        "max_y": 1239,
        "label": "roadLines"
    },
    {
        "id": "b_box_roadLines_102178",
        "min_x": 1078,
        "max_x": 1141,
        "min_y": 835,
        "max_y": 897,
        "label": "roadLines"
    },
    {
        "id": "b_box_roadLines_102178",
        "min_x": 661,
        "max_x": 729,
        "min_y": 835,
        "max_y": 898,
        "label": "roadLines"
    },
    {
        "id": "b_box_roadLines_102178",
        "min_x": 0,
        "max_x": 178,
        "min_y": 749,
        "max_y": 781,
        "label": "roadLines"
    },
    {
        "id": "b_box_roadLines_102178",
        "min_x": 1216,
        "max_x": 1819,
        "min_y": 745,
        "max_y": 999,
        "label": "roadLines"
    },
    {
        "id": "b_box_roadLines_102178",
        "min_x": 975,
        "max_x": 1112,
        "min_y": 666,
        "max_y": 756,
        "label": "roadLines"
    },
    {
        "id": "b_box_roadLines_102178",
        "min_x": 788,
        "max_x": 839,
        "min_y": 703,
        "max_y": 756,
        "label": "roadLines"
    },
    {
        "id": "b_box_roadLines_102178",
        "min_x": 581,
        "max_x": 628,
        "min_y": 740,
        "max_y": 757,
        "label": "roadLines"
    },
    {
        "id": "b_box_roadLines_102178",
        "min_x": 270,
        "max_x": 426,
        "min_y": 717,
        "max_y": 757,
        "label": "roadLines"
    }
]